cloud_identification.cpython-37m-x86_64-linux-gnu.so
cloud_identification-0.3.0.dist-info/METADATA
cloud_identification-0.3.0.dist-info/WHEEL
cloud_identification-0.3.0.dist-info/RECORD
cloud_identification-0.3.0.dist-info/LICENSE
cloud_identification-0.3.0.dist-info/top_level.txt
cloud_identification.libs/libgcc_s-a04fdf82.so.1
cloud_identification.libs/libstdc++-a9383cce.so.6.0.28
